{
	"configurations" : 
	[
		{
			"directories" : 
			[
				{
					"build" : ".",
					"projectIndex" : 0,
					"source" : "."
				}
			],
			"name" : "Debug",
			"projects" : 
			[
				{
					"directoryIndexes" : 
					[
						0
					],
					"name" : "Project"
				}
			],
			"targets" : []
		}
	],
	"kind" : "codemodel",
	"paths" : 
	{
		"build" : "C:/Users/gunny/Desktop/GameProgramming/P4/SLDProject/glm/out/build/x64-Debug",
		"source" : "C:/Users/gunny/Desktop/GameProgramming/P4/SLDProject/glm"
	},
	"version" : 
	{
		"major" : 2,
		"minor" : 2
	}
}
